pandana/__init__.py
pandana/cyaccess.cpython-311-darwin.so
pandana/network.py
pandana/testing.py
pandana/utils.py
pandana/loaders/__init__.py
pandana/loaders/osm.py
pandana/loaders/pandash5.py
pandana-0.7.dist-info/LICENSE.txt
pandana-0.7.dist-info/METADATA
pandana-0.7.dist-info/WHEEL
pandana-0.7.dist-info/top_level.txt
pandana-0.7.dist-info/RECORD
