Metadata-Version: 2.1
Name: pandana
Version: 0.7
Summary: Python library for network analysis
Home-page: https://udst.github.io/pandana/
Author: UrbanSim Inc.
License: AGPL
Classifier: Programming Language :: Python :: 3.6
Classifier: Programming Language :: Python :: 3.7
Classifier: Programming Language :: Python :: 3.8
Classifier: Programming Language :: Python :: 3.9
Classifier: Programming Language :: Python :: 3.10
Classifier: Programming Language :: Python :: 3.11
Classifier: License :: OSI Approved :: GNU Affero General Public License v3
License-File: LICENSE.txt
